{
    "backend": "flask",
    "db_name": "",
    "db_pass": "",
    "db_type": "",
    "db_user": "",
    "dbms": "0",
    "description": "generated product",
    "design": "soft-ui-dashboard",
    "docker": "1",
    "err_code": 0,
    "frontend": "",
    "heroku": "0",
    "pattern": "mvc",
    "pro": "0",
    "task_id": "57b79c3e-f570-48e5-a89a-745eff82f771",
    "task_info": "Upload Sources [0%] - 323 files",
    "task_output": "57b79c3e-f570-48e5-a89a-745eff82f771.zip",
    "task_result": "SUCCESS",
    "task_state": "RUNNING",
    "task_ts_end": "2023-10-31-07-41-58",
    "task_ts_start": "2023-10-31-07-41-55"
}